moonshine/__init__.py
moonshine/doomsday.py
moonshine/data/__init__.py
moonshine/data/flash.dat
moonshine_cli-1.0.2.dist-info/LICENSE
moonshine_cli-1.0.2.dist-info/METADATA
moonshine_cli-1.0.2.dist-info/WHEEL
moonshine_cli-1.0.2.dist-info/entry_points.txt
moonshine_cli-1.0.2.dist-info/top_level.txt
moonshine_cli-1.0.2.dist-info/RECORD
