Metadata-Version: 2.1
Name: moonshine-cli
Version: 1.0.2
Summary: moonshine Package extends main framework functionalities
Home-page: https://github.com/phantom-xyz/moonshine
Author: Phantom-X
Author-email: 0x01.phantom@gmail.com
Project-URL: Bug Reports, https://github.com/phantom-xyz/moonshine/issues
Project-URL: Funding, https://donate.pypi.org
Project-URL: Say Thanks!, http://saythanks.io/to/phantom-xyz
Keywords: moonshine Python development environment
Classifier: Development Status :: 3 - Alpha
Classifier: Environment :: Console
Classifier: Environment :: Web Environment
Classifier: Operating System :: Microsoft :: Windows
Classifier: Operating System :: MacOS :: MacOS X
Classifier: Operating System :: POSIX :: Linux
Classifier: Topic :: Communications :: Email
Classifier: Topic :: Office/Business
Classifier: Topic :: Software Development :: Bug Tracking
Classifier: License :: OSI Approved :: MIT License
Classifier: Programming Language :: Python :: 3.10
Requires-Python: >=3.8, <4
License-File: LICENSE
Provides-Extra: dev
Requires-Dist: check-manifest ; extra == 'dev'
Provides-Extra: test
Requires-Dist: coverage ; extra == 'test'
